src/__init__.py
src/ia/__init__.py
src/ia/ia_model.py
src/ia/tensorflow_s/__init__.py
src/ia/tensorflow_s/sequential_model.py
src/ia/tensorflow_s/sequential_space.py
src/ia/tensorflow_s/models/__init__.py
src/ia/tensorflow_s/models/multilayer/__init__.py
src/ia/tensorflow_s/models/multilayer/multilayer_dataset_parser.py
src/ia/tensorflow_s/models/multilayer/multilayer_perceptron_space.py
src/ia/tensorflow_s/models/multilayer/multilayer_perceptron_training.py
src/ia/tensorflow_s/multilevel/__init__.py
src/ia/tensorflow_s/multilevel/multilevel_sequential_training.py
src/ia/tensorflow_s/multilevel/sequential_data_parser.py
src/ia/train/__init__.py
src/ia/train/dataset.py
src/ia/train/prospect.py
src/ia/train/training_goal.py
src/ia/train/multilevel/__init__.py
src/ia/train/multilevel/dataparser.py
src/ia/train/multilevel/miltilevel_training.py
src/ia/train/multilevel/multilevel_ia_model.py
src/io/__init__.py
src/io/file_reader.py
src/io/reader.py
src/io/scanner.py
src/io/writer.py
src/io/google/__init__.py
src/io/google/google_api_connection.py
src/io/google/spread_sheet_connection.py
src/math/__init__.py
src/math/functions/__init__.py
src/math/functions/function.py
src/ocean/__init__.py
src/ocean/occean.py
src/search/__init__.py
src/search/goal.py
src/search/space/__init__.py
src/search/space/space.py
src/sort/__init__.py
src/sort/order.py
oceanai_py-0.0.5.dist-info/METADATA
oceanai_py-0.0.5.dist-info/WHEEL
oceanai_py-0.0.5.dist-info/top_level.txt
oceanai_py-0.0.5.dist-info/RECORD
