Metadata-Version: 2.1
Name: oceanai-py
Version: 0.0.5
Summary: Librería para conectarce a ocean protocol y poder crear IA
Home-page: https://github.com/itrm-team/oceanai-py
Author: ITRMachines
Author-email: matteo.murcia@gmail.com
License: MIT
Requires-Dist: numpy
Requires-Dist: wheel
